<?xml version="1.0" encoding="utf-8"?>
<root date="2016-5-12 13:12" hash="8ae987ca1535c3b7a98f7d7fd73a9a84">
  <row_0>
    <col_0>Шприц для смазки</col_0>
    <col_1>AGH-10003</col_1>
    <col_2>шт</col_2>
    <col_3>17.76930576</col_3>
    <col_4>470.8866025</col_4>
    <col_5>**</col_5>
  </row_0>
  <row_1>
    <col_0>Шприц для смазки с гибким шлангом</col_0>
    <col_1>AGH-10003H</col_1>
    <col_2>шт</col_2>
    <col_3>21.56142095</col_3>
    <col_4>571.3776552</col_4>
    <col_5>**</col_5>
  </row_1>
  <row_2>
    <col_0>Шприц для смазки с клапаном</col_0>
    <col_1>AGH-10004</col_1>
    <col_2>шт</col_2>
    <col_3>20.66198344</col_3>
    <col_4>547.5425611</col_4>
    <col_5>**</col_5>
  </row_2>
  <row_3>
    <col_0>Продувочный пистолет</col_0>
    <col_1>PAP-D004</col_1>
    <col_2>шт</col_2>
    <col_3>9.119772</col_3>
    <col_4>241.673958</col_4>
    <col_5>***</col_5>
  </row_3>
  <row_4>
    <col_0>Продувочный пистолет 250 мм</col_0>
    <col_1>PAP-D043-10P</col_1>
    <col_2>шт</col_2>
    <col_3>6.479598006</col_3>
    <col_4>171.7093472</col_4>
    <col_5>***</col_5>
  </row_4>
  <row_5>
    <col_0>Набор бит 1/4" с держателем, 32 пр.</col_0>
    <col_1>ABD-70001</col_1>
    <col_2>шт</col_2>
    <col_3>16.4155896</col_3>
    <col_4>435.0131244</col_4>
    <col_5>***</col_5>
  </row_5>
  <row_6>
    <col_0>Набор бит, 42 пр.</col_0>
    <col_1>ABS-80004</col_1>
    <col_2>шт</col_2>
    <col_3>41.39616507</col_3>
    <col_4>1096.998374</col_4>
    <col_5>***</col_5>
  </row_6>
  <row_7>
    <col_0>Телескопический магнит</col_0>
    <col_1>ATN-1016C</col_1>
    <col_2>шт</col_2>
    <col_3>4.882041946</col_3>
    <col_4>129.3741116</col_4>
    <col_5>****</col_5>
  </row_7>
  <row_8>
    <col_0>Набор ключей комбинированных 14 предметов 10-32 мм</col_0>
    <col_1>AWT-ERSK05</col_1>
    <col_2>шт</col_2>
    <col_3>80.13999645</col_3>
    <col_4>2123.709906</col_4>
    <col_5>****</col_5>
  </row_8>
  <row_9>
    <col_0>Набор ключей комбинированных 16 предметов 6-24 мм в металлическом ящике</col_0>
    <col_1>AWT-ERSK06</col_1>
    <col_2>шт</col_2>
    <col_3>56.14549633</col_3>
    <col_4>1487.855653</col_4>
    <col_5>*</col_5>
  </row_9>
  <row_10>
    <col_0>Набор ключей комбинированных 26 предметов 6-32 мм в скрутке</col_0>
    <col_1>AWT-ERSK04</col_1>
    <col_2>шт</col_2>
    <col_3>124.2796929</col_3>
    <col_4>3293.411863</col_4>
    <col_5>****</col_5>
  </row_10>
  <row_11>
    <col_0>Набор ключей комбинированных дюймовых 14 предметов 5/16-1-1/4"</col_0>
    <col_1>AWT-ERSK03</col_1>
    <col_2>шт</col_2>
    <col_3>77.26156841</col_3>
    <col_4>2047.431563</col_4>
    <col_5>*</col_5>
  </row_11>
  <row_12>
    <col_0>Набор ключей комбинированных текстурных в кейсе 26пр.</col_0>
    <col_1>AWT-ESFK05</col_1>
    <col_2>шт</col_2>
    <col_3>162.5884352</col_3>
    <col_4>4308.593532</col_4>
    <col_5>*</col_5>
  </row_12>
  <row_13>
    <col_0>Набор ключей накидных 75гр. 12пр., 6-32 мм</col_0>
    <col_1>AWT-EKFK02</col_1>
    <col_2>шт</col_2>
    <col_3>95.64360885</col_3>
    <col_4>2534.555635</col_4>
    <col_5>**</col_5>
  </row_13>
  <row_14>
    <col_0>Набор ключей разрезных текстурных 8-19 мм 5пр.</col_0>
    <col_1>AWT-EVFK01</col_1>
    <col_2>шт</col_2>
    <col_3>27.1313217</col_3>
    <col_4>718.9800251</col_4>
    <col_5>*</col_5>
  </row_14>
  <row_15>
    <col_0>Набор ключей рожковых 12 предметов 6-32 мм</col_0>
    <col_1>AWT-EDSK01</col_1>
    <col_2>шт</col_2>
    <col_3>60.77948048</col_3>
    <col_4>1610.656233</col_4>
    <col_5>*</col_5>
  </row_15>
  <row_16>
    <col_0>Набор ключей трещоточных  с полукарданом 72 зуба 7пр.</col_0>
    <col_1>ARW-12MK07</col_1>
    <col_2>шт</col_2>
    <col_3>90.91272713</col_3>
    <col_4>2409.187269</col_4>
    <col_5>*</col_5>
  </row_16>
  <row_17>
    <col_0>Набор ключей трещоточных комбинированных 72 зуба 8-19 мм, 7 предметов на пластиковом держателе</col_0>
    <col_1>ARW-11MK06</col_1>
    <col_2>шт</col_2>
    <col_3>64.57938548</col_3>
    <col_4>1711.353715</col_4>
    <col_5>*</col_5>
  </row_17>
  <row_18>
    <col_0>Набор торксов угловых длинных 9пр. T10-T50</col_0>
    <col_1>2TX20091DPM</col_1>
    <col_2>шт</col_2>
    <col_3>12.06545836</col_3>
    <col_4>319.7346464</col_4>
    <col_5>*</col_5>
  </row_18>
  <row_19>
    <col_0>Набор торксов угловых длинных с отверстием 9пр. T10-T50</col_0>
    <col_1>2TF20091DPM</col_1>
    <col_2>шт</col_2>
    <col_3>13.26083247</col_3>
    <col_4>351.4120605</col_4>
    <col_5>**</col_5>
  </row_19>
  <row_20>
    <col_0>Набор шестигранников угловых 13пр., 2-19 мм</col_0>
    <col_1>HW1M019H2S2</col_1>
    <col_2>шт</col_2>
    <col_3>36.05159869</col_3>
    <col_4>955.3673652</col_4>
    <col_5>*</col_5>
  </row_20>
  <row_21>
    <col_0>Набор шестигранников угловых длинных 9пр. 1,5-10 мм</col_0>
    <col_1>2HW20091DPM</col_1>
    <col_2>шт</col_2>
    <col_3>11.90905427</col_3>
    <col_4>315.5899381</col_4>
    <col_5>**</col_5>
  </row_21>
  <row_22>
    <col_0>Набор шестигранников угловых длинных c шаром 9пр. 1,5-10 мм</col_0>
    <col_1>2BP20091DPM</col_1>
    <col_2>шт</col_2>
    <col_3>11.80850878</col_3>
    <col_4>312.9254827</col_4>
    <col_5>**</col_5>
  </row_22>
  <row_23>
    <col_0>Набор шестигранников угловых длинных дюйм. 9пр. 1/16-3/8"</col_0>
    <col_1>HW2M092H2S2</col_1>
    <col_2>шт</col_2>
    <col_3>11.80850878</col_3>
    <col_4>312.9254827</col_4>
    <col_5>**</col_5>
  </row_23>
  <row_24>
    <col_0>Набор головок Е-профиль Е4-Е24 1/4", 3/8", 1/2" 14пр. на линейке</col_0>
    <col_1>TBS-11005</col_1>
    <col_2>шт</col_2>
    <col_3>15.61380965</col_3>
    <col_4>413.7659556</col_4>
    <col_5>**</col_5>
  </row_24>
  <row_25>
    <col_0>Набор торцевых головок 1/2" 12 гр. 10-24 мм 10пр. на линейке</col_0>
    <col_1>TBS-22005</col_1>
    <col_2>шт</col_2>
    <col_3>14.30664233</col_3>
    <col_4>379.1260216</col_4>
    <col_5>**</col_5>
  </row_25>
  <row_26>
    <col_0>Набор торцевых головок 1/2" 6 гр. 10-24 мм 10пр. на линейке</col_0>
    <col_1>TBS-22105</col_1>
    <col_2>шт</col_2>
    <col_3>13.96465088</col_3>
    <col_4>370.0632482</col_4>
    <col_5>**</col_5>
  </row_26>
  <row_27>
    <col_0>Набор торцевых головок 1/4" 6 гр. 5-14 мм 10пр. на линейке</col_0>
    <col_1>TBS-22101</col_1>
    <col_2>шт</col_2>
    <col_3>6.326841825</col_3>
    <col_4>167.6613084</col_4>
    <col_5>*</col_5>
  </row_27>
  <row_28>
    <col_0>Динамометрический ключ 1/2" 40-210Нм</col_0>
    <col_1>AQL-N4210</col_1>
    <col_2>шт</col_2>
    <col_3>72.17919548</col_3>
    <col_4>1912.74868</col_4>
    <col_5>*</col_5>
  </row_28>
  <row_29>
    <col_0>Динамометрический ключ 1/2" 70-350Нм</col_0>
    <col_1>AQL-N4350</col_1>
    <col_2>шт</col_2>
    <col_3>91.74217039</col_3>
    <col_4>2431.167515</col_4>
    <col_5>*</col_5>
  </row_29>
  <row_30>
    <col_0>Заклепочник рычажный промышленный 3,2-6,4 мм</col_0>
    <col_1>ART-0004</col_1>
    <col_2>шт</col_2>
    <col_3>70.05124868</col_3>
    <col_4>1856.35809</col_4>
    <col_5>**</col_5>
  </row_30>
  <row_31>
    <col_0>Заклепочник с поворотной головкой 360 2,4-4,8 мм NCG</col_0>
    <col_1>ART-0003</col_1>
    <col_2>шт</col_2>
    <col_3>26.39034023</col_3>
    <col_4>699.344016</col_4>
    <col_5>**</col_5>
  </row_31>
  <row_32>
    <col_0>Молоток с ручкой из дерева гикори 1000 г</col_0>
    <col_1>AHM-01000</col_1>
    <col_2>шт</col_2>
    <col_3>16.8516287</col_3>
    <col_4>446.5681605</col_4>
    <col_5>****</col_5>
  </row_32>
  <row_33>
    <col_0>Молоток с ручкой из дерева гикори 300 г</col_0>
    <col_1>AHM-00300</col_1>
    <col_2>шт</col_2>
    <col_3>9.548401284</col_3>
    <col_4>253.032634</col_4>
    <col_5>***</col_5>
  </row_33>
  <row_34>
    <col_0>Молоток с ручкой из дерева гикори 500 г</col_0>
    <col_1>AHM-00500</col_1>
    <col_2>шт</col_2>
    <col_3>11.90016249</col_3>
    <col_4>315.3543059</col_4>
    <col_5>***</col_5>
  </row_34>
  <row_35>
    <col_0>Молоток с ручкой из дерева гикори 800 г</col_0>
    <col_1>AHM-00800</col_1>
    <col_2>шт</col_2>
    <col_3>14.57643558</col_3>
    <col_4>386.2755429</col_4>
    <col_5>***</col_5>
  </row_35>
  <row_36>
    <col_0>Набор торцевых головок 1/2" 24пр. 10 - 32 мм</col_0>
    <col_1>ALT-5002F-RU</col_1>
    <col_2>шт</col_2>
    <col_3>79.9</col_3>
    <col_4>2117.35</col_4>
    <col_5>**</col_5>
  </row_36>
  <row_37>
    <col_0>Набор торцевых головок 3/4", 6гр., 22-50 мм, 15пр.</col_0>
    <col_1>ALT-6001F</col_1>
    <col_2>шт</col_2>
    <col_3>161.3419903</col_3>
    <col_4>4275.562744</col_4>
    <col_5>**</col_5>
  </row_37>
  <row_38>
    <col_0>Набор инструмента  1/2" и 1/4" 6 гр. 98 предметов</col_0>
    <col_1>ALK-0010F</col_1>
    <col_2>шт</col_2>
    <col_3>183.0224243</col_3>
    <col_4>4850.094245</col_4>
    <col_5>**</col_5>
  </row_38>
  <row_39>
    <col_0>Набор инструмента 1/2" и 1/4" 6 гр. 108 предметов</col_0>
    <col_1>ALK-0014F</col_1>
    <col_2>шт</col_2>
    <col_3>176.9235768</col_3>
    <col_4>4688.474785</col_4>
    <col_5>**</col_5>
  </row_39>
  <row_40>
    <col_0>Набор инструмента 1/2" и 1/4" 94 предмета</col_0>
    <col_1>ALK-8010F</col_1>
    <col_2>шт</col_2>
    <col_3>101.9134521</col_3>
    <col_4>2700.706481</col_4>
    <col_5>****</col_5>
  </row_40>
  <row_41>
    <col_0>Набор инструмента 1/4" и 1/2" 6 гр. 143 предмета</col_0>
    <col_1>ALK-8009F</col_1>
    <col_2>шт</col_2>
    <col_3>265.9268517</col_3>
    <col_4>7047.061569</col_4>
    <col_5>****</col_5>
  </row_41>
  <row_42>
    <col_0>Набор инструмента 1/4" и 1/2" 6 гр. 83 предмета</col_0>
    <col_1>ALK-8015F</col_1>
    <col_2>шт</col_2>
    <col_3>131.8947026</col_3>
    <col_4>3495.209618</col_4>
    <col_5>***</col_5>
  </row_42>
  <row_43>
    <col_0>Набор инструмента 1/4" и 1/2" 6гр. 113 предметов</col_0>
    <col_1>ALK-8011F</col_1>
    <col_2>шт</col_2>
    <col_3>149.1082722</col_3>
    <col_4>3951.369213</col_4>
    <col_5>****</col_5>
  </row_43>
  <row_44>
    <col_0>Набор инструмента 1/4" и 1/2" 6гр. 81 предмет</col_0>
    <col_1>ALK-8016F</col_1>
    <col_2>шт</col_2>
    <col_3>170.7107321</col_3>
    <col_4>4523.834401</col_4>
    <col_5>*</col_5>
  </row_44>
  <row_45>
    <col_0>Набор инструмента 1/4" и 1/2" 6гр. 89 предметов</col_0>
    <col_1>ALK-8008F</col_1>
    <col_2>шт</col_2>
    <col_3>199.4950125</col_3>
    <col_4>5286.617831</col_4>
    <col_5>***</col_5>
  </row_45>
  <row_46>
    <col_0>Набор отверток профессиональных 8пр.</col_0>
    <col_1>ASD-900K2</col_1>
    <col_2>шт</col_2>
    <col_3>33.23016923</col_3>
    <col_4>880.5994845</col_4>
    <col_5>***</col_5>
  </row_46>
  <row_47>
    <col_0>Набор отверток усиленных цельнометаллических 7пр.</col_0>
    <col_1>ASD-600K1</col_1>
    <col_2>шт</col_2>
    <col_3>47.4228144</col_3>
    <col_4>1256.704582</col_4>
    <col_5>**</col_5>
  </row_47>
  <row_48>
    <col_0>Ударная отвертка и 6 бит в пласт. кейсе</col_0>
    <col_1>ABD-73003</col_1>
    <col_2>шт</col_2>
    <col_3>24.8235634</col_3>
    <col_4>657.82443</col_4>
    <col_5>***</col_5>
  </row_48>
  <row_49>
    <col_0>Бокорезы 140 мм</col_0>
    <col_1>APT-36005A</col_1>
    <col_2>шт</col_2>
    <col_3>9.404764875</col_3>
    <col_4>249.2262692</col_4>
    <col_5>**</col_5>
  </row_49>
  <row_50>
    <col_0>Бокорезы 160 мм</col_0>
    <col_1>APT-36005B</col_1>
    <col_2>шт</col_2>
    <col_3>10.03858903</col_3>
    <col_4>266.0226093</col_4>
    <col_5>**</col_5>
  </row_50>
  <row_51>
    <col_0>Бокорезы 180 мм</col_0>
    <col_1>APT-36005C</col_1>
    <col_2>шт</col_2>
    <col_3>11.399715</col_3>
    <col_4>302.0924475</col_4>
    <col_5>**</col_5>
  </row_51>
  <row_52>
    <col_0>Длинногубцы 200 мм</col_0>
    <col_1>APT-36002C</col_1>
    <col_2>шт</col_2>
    <col_3>11.84202394</col_3>
    <col_4>313.8136345</col_4>
    <col_5>**</col_5>
  </row_52>
  <row_53>
    <col_0>Плоскогубцы комбинированные 160 мм</col_0>
    <col_1>APT-36001B</col_1>
    <col_2>шт</col_2>
    <col_3>10.32266993</col_3>
    <col_4>273.5507531</col_4>
    <col_5>**</col_5>
  </row_53>
  <row_54>
    <col_0>Плоскогубцы комбинированные 180 мм</col_0>
    <col_1>APT-36001C</col_1>
    <col_2>шт</col_2>
    <col_3>10.99297317</col_3>
    <col_4>291.313789</col_4>
    <col_5>**</col_5>
  </row_54>
  <row_55>
    <col_0>Плоскогубцы комбинированные 200 мм</col_0>
    <col_1>APT-36001D</col_1>
    <col_2>шт</col_2>
    <col_3>14.09871152</col_3>
    <col_4>373.6158554</col_4>
    <col_5>**</col_5>
  </row_55>
  <row_56>
    <col_0>Переставные клещи 240 мм</col_0>
    <col_1>APT-36010B</col_1>
    <col_2>шт</col_2>
    <col_3>16.8916417</col_3>
    <col_4>447.628505</col_4>
    <col_5>***</col_5>
  </row_56>
  <row_57>
    <col_0>Ручные тиски струбцина 175 мм</col_0>
    <col_1>APT-39002B</col_1>
    <col_2>шт</col_2>
    <col_3>9.149639253</col_3>
    <col_4>242.4654402</col_4>
    <col_5>***</col_5>
  </row_57>
  <row_58>
    <col_0>Ручные тиски струбцина 250 мм</col_0>
    <col_1>APT-39002C</col_1>
    <col_2>шт</col_2>
    <col_3>11.91270218</col_3>
    <col_4>315.6866076</col_4>
    <col_5>***</col_5>
  </row_58>
  <row_59>
    <col_0>Съемник стопорных колец разжим 180 мм</col_0>
    <col_1>APT-38003B</col_1>
    <col_2>шт</col_2>
    <col_3>10.13275067</col_3>
    <col_4>268.5178929</col_4>
    <col_5>***</col_5>
  </row_59>
  <row_60>
    <col_0>Съемник стопорных колец разжим, загнутые 180 мм</col_0>
    <col_1>APT-38004B</col_1>
    <col_2>шт</col_2>
    <col_3>9.547261313</col_3>
    <col_4>253.0024248</col_4>
    <col_5>***</col_5>
  </row_60>
  <row_61>
    <col_0>Съемник стопорных колец сжим 180 мм</col_0>
    <col_1>APT-38001B</col_1>
    <col_2>шт</col_2>
    <col_3>9.433264163</col_3>
    <col_4>249.9815003</col_4>
    <col_5>***</col_5>
  </row_61>
  <row_62>
    <col_0>Съемник стопорных колец сжим, загнутые 180 мм</col_0>
    <col_1>APT-38002B</col_1>
    <col_2>шт</col_2>
    <col_3>9.632759175</col_3>
    <col_4>255.2681181</col_4>
    <col_5>***</col_5>
  </row_62>
  <row_63>
    <col_0>Съемник масляных фильтров "краб" с тонкими ножками 63-100 мм</col_0>
    <col_1>ATA-0257A</col_1>
    <col_2>шт</col_2>
    <col_3>10.59079122</col_3>
    <col_4>280.6559674</col_4>
    <col_5>**</col_5>
  </row_63>
  <row_64>
    <col_0>Съемник масляных фильтров ременной профессиональный 25-160 мм</col_0>
    <col_1>ATA-0265</col_1>
    <col_2>шт</col_2>
    <col_3>13.28066798</col_3>
    <col_4>351.9377013</col_4>
    <col_5>***</col_5>
  </row_64>
</root>
